snowconn/__init__.py
snowconn/connect.py
snowconn/connection_builder.py
snowconn/py.typed
snowconn-3.14.2.dist-info/METADATA
snowconn-3.14.2.dist-info/WHEEL
snowconn-3.14.2.dist-info/licenses/LICENSE
snowconn-3.14.2.dist-info/RECORD
