Metadata-Version: 2.4
Name: snowconn
Version: 3.14.2
Summary: Python utilities for connection to the Snowflake data warehouse
Project-URL: Homepage, https://github.com/daltix/snowconn
Project-URL: Documentation, https://github.com/daltix/snowconn
Project-URL: Repository, https://github.com/daltix/snowconn
Project-URL: Bug Tracker, https://github.com/daltix/snowconn/issues
Project-URL: License, https://github.com/daltix/snowconn/blob/master/LICENSE.md
Author-email: Daltix NV <snowconn@daltix.com>
Maintainer-email: Daltix NV <snowconn@daltix.com>
License: MIT License
License-File: LICENSE
Requires-Python: >=3.8
Requires-Dist: cryptography<42,>=41
Requires-Dist: snowflake-connector-python<3.14,>=3.0.4
Requires-Dist: snowflake-sqlalchemy<1.8,>=1.4.7
Requires-Dist: sqlalchemy
Provides-Extra: all
Requires-Dist: boto3; extra == 'all'
Requires-Dist: snowflake-connector-python[pandas,secure-local-storage]<3.14,>=3.0.4; extra == 'all'
Provides-Extra: pandas
Requires-Dist: pandas; extra == 'pandas'
Requires-Dist: snowflake-connector-python[pandas]<3.14,>=3.0.4; extra == 'pandas'
Provides-Extra: storage
Requires-Dist: snowflake-connector-python[secure-local-storage]<3.14,>=3.0.4; extra == 'storage'
